traefikswarm/__init__.py
traefikswarm/__main__.py
traefikswarm/command_line.py
traefikswarm/context.py
traefikswarm/dockertools.py
traefikswarm/commands/__init__.py
traefikswarm/commands/config.py
traefikswarm/commands/expose.py
traefikswarm/commands/forwarder.py
traefikswarm/commands/service.py
traefikswarm/commands/unexpose.py
traefikswarm-0.0.10.dist-info/LICENSE.txt
traefikswarm-0.0.10.dist-info/METADATA
traefikswarm-0.0.10.dist-info/WHEEL
traefikswarm-0.0.10.dist-info/entry_points.txt
traefikswarm-0.0.10.dist-info/top_level.txt
traefikswarm-0.0.10.dist-info/RECORD
