Metadata-Version: 2.1
Name: traefikswarm
Version: 0.0.10
Summary: A simple tool to manage traefik in a docker swarm
Home-page: https://github.com/ssimek/traefikswarm
Author: Štefan Šimek
Author-email: simek@triaxis.sk
License: MIT
Platform: UNKNOWN
Classifier: Programming Language :: Python :: 3
Classifier: License :: OSI Approved :: MIT License
Classifier: Operating System :: OS Independent
Requires-Python: >=3.6
Requires-Dist: docker (>=4)
